{
    "id": "monoteismens-fodsel",
    "title": "Hadde Gud en kone?",
    "subject": "krle",
    "topic": "religion",
    "religion": "historiske-religioner",
    "layout": "rich",
    "year": "ca. 700 f.Kr.",
    "category": "Religionshistorie",
    "readTime": "14 min lesning",
    "heroImage": "/images/placeholder.webp",
    "dimension": "narrative",
    "comparison_tags": [
        "gudsbildet",
        "monoteisme",
        "kilder-til-tro",
        "religioners-utvikling"
    ],
    "details": [
        "Arkeologer har funnet inskripsjoner som nevner «Yahweh og hans Asherah» - en gudinne ved Guds side.",
        "I de eldste tekstene har Gud en kropp: han går, snakker, gråter og hviler.",
        "Den egyptiske faraoen Akhenaten dyrket bare én gud nesten 700 år før jødedommen ble til.",
        "De fleste forskere mener monoteismen vokste sakte fram over mange hundre år, ikke på én dag.",
        "Forskere studerer dette med kilder og arkeologi. Det forteller hvordan troen utviklet seg, ikke om Gud finnes."
    ],
    "content": [
        {
            "type": "header",
            "text": "Et mystisk funn i ørkenen"
        },
        {
            "type": "text",
            "content": "En gang på 700-tallet før vår tidsregning satt noen i en liten rasteplass i Sinai-ørkenen og skrev på en stor krukke. Stedet heter Kuntillet Ajrud. Da arkeologer gravde det fram på 1970-tallet, fant de en setning som fikk forskere over hele verden til å studse. Det sto: «Jeg velsigner deg ved Yahweh av Samaria og hans Asherah.»"
        },
        {
            "type": "text",
            "content": "Yahweh er navnet på Gud i Det gamle testamentet. Men hvem var Asherah? Og hvorfor sto hun ved siden av Gud, nesten som en partner? For mange er Gud i dag én eneste, usynlig kraft uten kropp og uten familie. Funnet i ørkenen peker mot noe annet: at folk en gang trodde at Gud hadde en gudinne ved sin side. Dette kapittelet handler om hva forskere har gravd fram om Guds egen historie. Husk hele veien at vi her ser på hvordan troen utviklet seg gjennom historien. Det er noe annet enn spørsmålet om Gud finnes, som hver enkelt må svare på selv."
        },
        {
            "type": "component",
            "name": "AsherahUtgraving",
            "props": {
                "title": "Asherah-utgravingen",
                "intro": "Børst bort jorda og grav fram bevisene for Yahwehs glemte gudinne."
            }
        },
        {
            "type": "header",
            "text": "Gud hadde en kropp"
        },
        {
            "type": "text",
            "content": "Den britiske forskeren Francesca Stavrakopoulou er professor i hebraisk bibel ved et universitet i England. I boka «God: An Anatomy» fra 2021 gjør hun noe uvanlig: hun leser de eldste tekstene om Gud bokstavelig, og ser etter hvordan folk faktisk så ham for seg. Det hun finner, overrasker mange."
        },
        {
            "type": "text",
            "content": "I de eldste delene av Bibelen har Gud en kropp. Han går rundt i Edens hage i den kjølige kveldsbrisen. Han snakker med Moses ansikt til ansikt, slik en venn snakker med en venn. Han strekker ut hånda si, han puster, han hviler den sjuende dagen, og han kan til og med bli sint og angre. Gud blir beskrevet som en mektig konge på en trone, distinkt mannlig, med følelser og en vilje."
        },
        {
            "type": "text",
            "content": "Eksemplene er mange. I én fortelling spiser Gud sammen med Abraham under et tre. I en annen ber Moses om å få se Gud, men får bare se ryggen hans, fordi det å se ansiktet ville vært for sterkt. Profeten Jesaja forteller at han så Gud sitte på en høy trone, og at kappekanten alene fylte hele tempelet. Dette er ikke beskrivelser av en tåke eller en følelse. Det er beskrivelser av en skikkelse med rygg, ansikt og klær."
        },
        {
            "type": "text",
            "content": "Stavrakopoulou mener at denne kroppslige Guden var den opprinnelige. Tanken om Gud som en usynlig, abstrakt kraft uten kropp kom mye senere. Den ble formet av blant annet gresk filosofi, lenge etter at de første tekstene ble skrevet. Med andre ord: bildet av Gud har forandret seg gjennom historien, akkurat som alt annet mennesker tror på og forteller videre."
        },
        {
            "type": "component",
            "name": "FactBox",
            "props": {
                "title": "Boka bak kapittelet",
                "items": [
                    {
                        "label": "Tittel",
                        "value": "«God: An Anatomy» (2021)"
                    },
                    {
                        "label": "Forfatter",
                        "value": "Francesca Stavrakopoulou, professor i hebraisk bibel"
                    },
                    {
                        "label": "Hovedidé",
                        "value": "Den eldste Yahweh ble sett på som mannlig og fysisk, med kropp og følelser."
                    },
                    {
                        "label": "TV-serie",
                        "value": "Hun har også laget BBC-serien «Bible's Buried Secrets»."
                    }
                ]
            }
        },
        {
            "type": "header",
            "text": "Yahweh og hans Asherah"
        },
        {
            "type": "text",
            "content": "La oss komme tilbake til gudinnen. Asherah var en kjent gudinne i hele området der israelittene bodde. Hun var moder-gudinne og ble dyrket av mange folk i Midtøsten. Det spesielle er at hun ikke bare ble dyrket ved siden av Yahweh, men sammen med ham."
        },
        {
            "type": "text",
            "content": "Inskripsjonen fra Kuntillet Ajrud er ikke alene. Et annet sted, Khirbet el-Qom, fant arkeologer en lignende tekst hugget inn i en grav. Også der nevnes «Yahweh og hans Asherah». To uavhengige funn, to ulike steder, samme budskap. Det er nettopp slik forskere bygger tillit til en kilde: når flere kilder som ikke kjenner hverandre, forteller det samme."
        },
        {
            "type": "text",
            "content": "Ifølge Kongebøkene i Bibelen sto det til og med en Asherah-statue inne i Yahwehs tempel i Jerusalem. Tekstene forteller at kvinner vevde rituelle tekstiler for henne der. Asherah var altså ikke gjemt bort i en avkrok. Hun sto midt i det helligste rommet. I tillegg har arkeologer funnet hundrevis av små leirfigurer av en kvinne i vanlige hjem i Juda. Gudinnen var like mye hjemme hos folk flest som i tempelet."
        },
        {
            "type": "text",
            "content": "Men noe skjedde. Over tid ble Asherah renset ut av troen. Ordet «asherah» dukker opp rundt 40 ganger i Bibelen, og nesten alltid blir det fordømt. Statuer skulle hogges ned, hellige pæler skulle brennes. Det at hun ble bekjempet så hardt, forteller paradoksalt nok at hun en gang var viktig. Du trenger ikke forby noe som ingen bryr seg om. Denne renselsen henger tett sammen med at troen langsomt ble til ren monoteisme: troen på én eneste Gud."
        },
        {
            "type": "header",
            "text": "El, den eldste guden"
        },
        {
            "type": "text",
            "content": "For å forstå hvorfor en gudinne kunne stå sammen med Yahweh, må vi møte en tredje gud: El. El var den øverste guden hos kanaaneerne, folkene som bodde i området før og samtidig med israelittene. Han ble sett som en gammel og vis far-gud, og gudinnen Asherah var kona hans. Legg merke til navnet hans. Ordet «el» betyr rett og slett «gud» på hebraisk. Du finner det igjen i «Elohim», et av navnene på Gud i Bibelen, og til og med i selve navnet Israel."
        },
        {
            "type": "text",
            "content": "Mange forskere mener at Yahweh og El smeltet sammen over tid. Yahweh overtok rollen til El som den høyeste guden, og arvet samtidig flere av trekkene hans. Kanskje arvet han også gudinnen Asherah, som egentlig hørte til El. Det ville forklare hvorfor hun dukker opp ved Yahwehs side på krukker og i graver. Bildet av Gud ble altså satt sammen av eldre byggesteiner, lenge før noen samlet dem i en bok."
        },
        {
            "type": "component",
            "name": "QuoteBlock",
            "props": {
                "text": "Jeg velsigner deg ved Yahweh av Samaria og hans Asherah.",
                "author": "Innskrift på en krukke, Kuntillet Ajrud (ca. 700-tallet f.Kr.)"
            }
        },
        {
            "type": "text",
            "content": "I mikrospillet under kan du selv gjenskape en av de viktigste hendelsene i denne historien. Kong Josjia gjennomførte en stor reform rundt år 622 før vår tidsregning. Han ville at folk bare skulle dyrke Yahweh. Klikk deg gjennom offerhøyden, og se hvordan mange guder ble til én."
        },
        {
            "type": "component",
            "name": "MicroGame",
            "props": {
                "gameId": "tempelets-renselse-3d"
            }
        },
        {
            "type": "header",
            "text": "Verdens første monoteist?"
        },
        {
            "type": "text",
            "content": "Hvis monoteismen vokste sakte fram, hvor begynte den egentlig? En spennende kandidat finnes i Egypt. Faraoen Akhenaten styrte rundt 1350 før vår tidsregning. Han gjorde noe ingen hadde gjort før: han beordret alle til å slutte å dyrke de gamle egyptiske gudene og i stedet tilbe bare én gud, solskiven Aten. Han bygde en helt ny hovedstad og lot kunstnerne lage bilder bare av Aten og sin egen familie. Derfor kaller noen ham verdens første monoteist."
        },
        {
            "type": "text",
            "content": "Akhenaten fikk kunstnerne til å vise Aten som en solskive med stråler som endte i små hender, og han skrev en vakker hymne til solguden. Men makten hvilte på ham alene. Eksperimentet varte ikke lenge. Akhenatens monoteisme ble påtvunget ovenfra av én eneveldig hersker. Da han døde, vendte folk raskt tilbake til de gamle gudene, og hans nye religion visnet på rot. Det er en viktig forskjell fra historien om Yahweh, som vi snart skal se."
        },
        {
            "type": "header",
            "text": "Freuds dristige idé"
        },
        {
            "type": "text",
            "content": "Akhenatens enegud har inspirert noen ganske vågale teorier. Den mest berømte kom fra Sigmund Freud, mannen som grunnla psykoanalysen. I boka «Moses and Monotheism» fra 1939 foreslo Freud at Moses egentlig var en egyptisk adelsmann og tilhenger av Akhenatens Aten-religion. Da denne religionen ble forbudt i Egypt, skal Moses ha flyktet sammen med tilhengerne sine og ført ideen om én gud videre til et nytt folk."
        },
        {
            "type": "text",
            "content": "Det er en fascinerende tanke, men det er viktig å være ærlig om hva den er: en teori, ikke et bevis. Freud var ingen historiker, og de fleste forskere i dag mener at koblingen hans er gjetting. Den viser likevel hvor sterkt mennesker ønsker å finne ett enkelt øyeblikk der monoteismen ble født. Virkeligheten er trolig mer rotete og mer interessant."
        },
        {
            "type": "header",
            "text": "Derfor er historikere skeptiske"
        },
        {
            "type": "text",
            "content": "Hvorfor tror de fleste forskere ikke at jødedommen bare kopierte Akhenaten? Tidslinjen passer dårlig. Arkeologien tyder på at israelittene ikke ble et eget folk før rundt 1200 før vår tidsregning. Det er over hundre år etter at Akhenaten døde, og i et helt annet land. Ideene hadde ingen lett vei å vandre langs."
        },
        {
            "type": "text",
            "content": "Det finnes også spor i Bibelen selv. Da Moses og folket synger en seierssang etter å ha krysset Rødehavet, synger de: «Hvem er som du blant gudene, Herre?» Legg merke til ordet «gudene». Sangen tar det for gitt at det finnes andre guder. Yahweh er bare den største og sterkeste av dem. Dette kalles henoteisme: troen på at flere guder finnes, men at man dyrker bare én av dem. Mange forskere mener dette var et viktig mellomtrinn på veien mot ren monoteisme."
        },
        {
            "type": "text",
            "content": "Israelittisk monoteisme utviklet seg altså langsomt, over mange hundre år. Den vokste fram gjennom diskusjoner, kriser og møter med andre folk. Da israelittene ble ført i fangenskap til Babylon på 500-tallet før vår tidsregning, måtte de tenke nytt om hvem Gud var når de var langt hjemmefra. Slike kriser formet troen. I motsetning til Akhenatens påtvungne enegud, var dette en tro som ble bygd nedenfra og holdt ut nettopp fordi den hadde slått dype røtter."
        },
        {
            "type": "component",
            "name": "QuoteBlock",
            "props": {
                "text": "Hvem er som du blant gudene, Herre?",
                "author": "Moses' seierssang, 2. Mosebok 15,11"
            }
        },
        {
            "type": "component",
            "name": "Comparison",
            "props": {
                "title": "To bilder av Gud",
                "leftTitle": "Gudsbildet mange har i dag",
                "rightTitle": "Bildet tekstene og arkeologien gir",
                "items": [
                    {
                        "label": "Kropp",
                        "left": "Usynlig, uten kropp, en abstrakt åndelig kraft.",
                        "right": "Har kropp i de eldste tekstene: går, snakker, hviler og puster."
                    },
                    {
                        "label": "Familie",
                        "left": "Helt alene, uten partner.",
                        "right": "Inskripsjoner nevner «Yahweh og hans Asherah», en gudinne ved hans side."
                    },
                    {
                        "label": "Andre guder",
                        "left": "Den eneste guden som finnes.",
                        "right": "Eldste tekster forutsetter at andre guder også finnes."
                    },
                    {
                        "label": "Hvordan det ble til",
                        "left": "Slik har det alltid vært.",
                        "right": "Vokste fram sakte over mange hundre år."
                    }
                ]
            }
        },
        {
            "type": "header",
            "text": "Gudens kulturelle DNA"
        },
        {
            "type": "text",
            "content": "Stavrakopoulou bruker et fint bilde: hun sier at Gud har et kulturelt DNA. Akkurat som du har arvet trekk fra slekta di, har bildet av Gud arvet trekk fra kulturene rundt det gamle Israel. Måten Gud blir beskrevet på, ligner på hvordan naboene beskrev sine guder. Han troner som en konge, han fører krig, han hersker over vær og hav, slik mange guder i Midtøsten gjorde."
        },
        {
            "type": "text",
            "content": "Dette arvegodset kom fra mange kanter. Babylonsk fortellerkunst, egyptiske ideer, kanaaneisk religion og senere gresk filosofi satte alle sine spor i det som til slutt ble Bibelen vi kjenner. Tanken er ikke at noen jukset eller fant på alt. Tanken er at religion, som språk og musikk, alltid blir til i samtale med verden rundt. Du finner de samme polyteistiske naboene i andre kapitler i denne boka, både hos [de romerske gudene](/historie/romerriket/romerske-guder) og i [åsatru hos vikingene](/historie/vikingtiden/asatro)."
        },
        {
            "type": "text",
            "content": "Et tydelig eksempel er fortellingen om den store flommen. Lenge før Bibelen ble skrevet, fortalte babylonerne om en mann som bygde en stor båt og berget livet da gudene sendte en flom over jorden. Fortellingen om Noah ligner påfallende. Det betyr ikke at den ene bare kopierte den andre, men at fortellingene levde i den samme verden og påvirket hverandre. Slik deler kulturer ideer, bilder og fortellinger på tvers av grenser, helt til de blir så kjente at vi glemmer hvor de kom fra."
        },
        {
            "type": "component",
            "name": "TimelineComponent",
            "props": {
                "compact": true,
                "events": [
                    {
                        "year": "ca. 1350 f.Kr.",
                        "title": "Akhenatens enegud",
                        "description": "Faraoen Akhenaten i Egypt påbyr at folk bare skal dyrke solguden Aten."
                    },
                    {
                        "year": "ca. 1200 f.Kr.",
                        "title": "Israelittene trer fram",
                        "description": "Arkeologien viser at israelittene blir et eget folk i høylandet."
                    },
                    {
                        "year": "ca. 700 f.Kr.",
                        "title": "«Yahweh og hans Asherah»",
                        "description": "Inskripsjoner i Kuntillet Ajrud og Khirbet el-Qom nevner Gud og gudinnen sammen."
                    },
                    {
                        "year": "ca. 622 f.Kr.",
                        "title": "Josjias reform",
                        "description": "Kong Josjia renser tempelet og vil at folk bare skal dyrke Yahweh."
                    },
                    {
                        "year": "587 f.Kr.",
                        "title": "Fangenskapet i Babylon",
                        "description": "Folket føres bort, og krisen tvinger fram en ny og renere monoteisme."
                    }
                ]
            }
        },
        {
            "type": "header",
            "text": "Hva betyr dette?"
        },
        {
            "type": "text",
            "content": "Det er lett å lese et kapittel som dette og tro at forskerne prøver å bevise at Gud ikke finnes. Det gjør de ikke. Arkeologi og kildekritikk kan vise oss hvordan mennesker har trodd, og hvordan troen har endret seg gjennom tidene. Men de kan ikke svare på det store spørsmålet om Gud er virkelig. Det spørsmålet ligger utenfor det forskere kan måle, og hver enkelt må tenke gjennom det selv."
        },
        {
            "type": "text",
            "content": "For en troende kan tanken om at gudsbildet har en historie til og med være vakker. Den viser at mennesker i tusenvis av år har strevd med å forstå noe større enn seg selv, og at forståelsen har vokst og modnet. For en som ikke tror, er det en spennende fortelling om hvordan ideer blir til og forandrer seg. Uansett hva du selv mener: når du neste gang hører ordet Gud, vet du nå at bak det ligger en lang og overraskende historie - en historie der det en gang sto en gudinne ved siden av ham."
        },
        {
            "type": "component",
            "name": "Quiz",
            "props": {
                "title": "Test deg selv: Guds glemte historie",
                "questions": [
                    {
                        "question": "Hva sto det på krukken fra Kuntillet Ajrud?",
                        "options": [
                            "«Yahweh er den eneste gud»",
                            "«Jeg velsigner deg ved Yahweh og hans Asherah»",
                            "«Asherah er sterkere enn Yahweh»",
                            "«Det finnes ingen guder»"
                        ],
                        "correctAnswer": 1,
                        "explanation": "Inskripsjonen nevner Yahweh og gudinnen Asherah sammen, nesten som et gudepar. Et lignende funn fra Khirbet el-Qom peker samme vei."
                    },
                    {
                        "question": "Hvordan beskrives Gud i de eldste tekstene, ifølge Stavrakopoulou?",
                        "options": [
                            "Som en usynlig, abstrakt kraft",
                            "Som en kvinne",
                            "Med en kropp: han går, snakker og hviler",
                            "Som flere guder i én"
                        ],
                        "correctAnswer": 2,
                        "explanation": "I de eldste tekstene har Gud en kropp og følelser. Bildet av en kroppløs, abstrakt Gud kom senere, blant annet fra gresk filosofi."
                    },
                    {
                        "question": "Hvorfor er de fleste historikere skeptiske til at jødedommen bare kopierte Akhenaten?",
                        "options": [
                            "Akhenaten fantes ikke",
                            "Israelittene ble et eget folk over hundre år senere og i et annet land",
                            "Egypterne var ikke religiøse",
                            "Freud beviste at det var feil"
                        ],
                        "correctAnswer": 1,
                        "explanation": "Tidslinjen passer dårlig. Israelittene trådte fram rundt 1200 f.Kr., lenge etter Akhenaten, og monoteismen deres vokste sakte fram over mange hundre år."
                    },
                    {
                        "question": "Hva betyr henoteisme?",
                        "options": [
                            "At det ikke finnes noen guder",
                            "At man tror flere guder finnes, men dyrker bare én",
                            "At alle guder er like sterke",
                            "At man dyrker solen"
                        ],
                        "correctAnswer": 1,
                        "explanation": "Henoteisme var trolig et mellomtrinn: Moses' sang spør «hvem er som du blant gudene», og tar dermed for gitt at andre guder finnes."
                    },
                    {
                        "question": "Hva kan arkeologi og kildekritikk fortelle oss om Gud?",
                        "options": [
                            "Om Gud finnes eller ikke",
                            "Hvordan troen og gudsbildet har endret seg gjennom historien",
                            "Hva Gud tenker",
                            "Ingenting i det hele tatt"
                        ],
                        "correctAnswer": 1,
                        "explanation": "Forskning kan vise hvordan mennesker har trodd og hvordan troen utviklet seg. Spørsmålet om Gud finnes, må hver enkelt svare på selv."
                    }
                ]
            }
        }
    ],
    "timeline": [],
    "quiz": [
        {
            "question": "Hva sto det på krukken fra Kuntillet Ajrud?",
            "options": [
                "«Yahweh er den eneste gud»",
                "«Jeg velsigner deg ved Yahweh og hans Asherah»",
                "«Det finnes ingen guder»"
            ],
            "answer": "«Jeg velsigner deg ved Yahweh og hans Asherah»"
        },
        {
            "question": "Hvordan beskrives Gud i de eldste tekstene?",
            "options": [
                "Som en usynlig, abstrakt kraft",
                "Med en kropp: han går, snakker og hviler",
                "Som flere guder i én"
            ],
            "answer": "Med en kropp: han går, snakker og hviler"
        },
        {
            "question": "Hva kan arkeologi fortelle oss om Gud?",
            "options": [
                "Om Gud finnes",
                "Hvordan troen har endret seg gjennom historien",
                "Hva Gud tenker"
            ],
            "answer": "Hvordan troen har endret seg gjennom historien"
        }
    ],
    "createdDate": "2026-06-15T00:00:00Z",
    "lastUpdated": "2026-06-15T00:00:00Z"
}
