{
    "id": "korea-dmz",
    "title": "DMZ: Grensen verden glemte å åpne",
    "subject": "historie",
    "layout": "rich",
    "year": "1953–i dag",
    "category": "Korea / Delte samfunn",
    "readTime": "11 min lesning",
    "heroImage": "/images/lessons/den-kalde-krigen/korea-dmz.webp",
    "details": [
        "DMZ (demilitarisert sone) er 250 km lang og 4 km bred.",
        "Korea er teknisk sett fortsatt i krig – det ble aldri signert en fredsavtale.",
        "Millioner av koreanske familier ble splittet av krigen og har aldri møttes igjen.",
        "Ironisk nok er DMZ blitt et naturreservat – fordi ingen mennesker kan gå der.",
        "Nord-Korea testet sin første atombombe i 2006."
    ],
    "timeline": [],
    "externalUrl": "https://snl.no/Korea-krigen",
    "content": [
        {
            "type": "text",
            "content": "Det er verdens mest militariserte grense. Begge sider av den smale sonen har hundretusener av soldater, miner, artilleri og avanserte våpensystemer. Og midt i denne dødsfellen – en stripe på fire kilometer der ingen mennesker kan ferdes – har naturen overtatt.\n\nDMZ, den demilitariserte sonen mellom Nord- og Sør-Korea, er et paradoks: Den ble skapt for å skille to arméer. Den har blitt et av Asias tetteste naturreservater. Den deler et folk som snakker samme språk. Og krigen den ble skapt av er teknisk sett aldri avsluttet. Les mer om krigen som skapte den hos [koreakrigen](/historie/den-kalde-krigen/koreakrigen)."
        },
        {
            "type": "component",
            "name": "FactBox",
            "props": {
                "title": "Hva er DMZ?",
                "content": "DMZ (Demilitarized Zone) er en 250 km lang og 4 km bred buffersone som ble etablert i 1953 som en del av våpenhvileavtalen etter Koreakrigen. Sonen er offisielt demilitarisert – men i realiteten er det den mest militariserte grensen i verden, med over en million soldater totalt på begge sider, samt landminer og overvåkningssystemer. Det finnes ingen fredsavtale mellom Nord- og Sør-Korea – bare en våpenhvile, som betyr at de to statene er i en teknisk krigstilstand den dag i dag."
            }
        },
        {
            "type": "header",
            "text": "Krigen som aldri ble avsluttet"
        },
        {
            "type": "text",
            "content": "Da Koreakrigen brøt ut i 1950, ble en halvøy kastet inn i tre år med brutal krig der USA, Kina og Sovjet alle var involvert. Da kampene stoppet i 1953, lå fronten omtrent der den hadde ligget ved krigsutbruddet – langs 38. breddegrad.\n\nMen det ble aldri signert en fredsavtale. Bare en våpenhvile. Det betyr at Nord- og Sør-Korea teknisk sett fortsatt er i krig – 70 år etter at skytingen stoppet. Sonen som ble trukket langs 38. breddegrad, ble til DMZ: et niemannsland som deler en halvøy og et folk."
        },
        {
            "type": "component",
            "name": "TimelineComponent",
            "props": {
                "title": "Korea og DMZ: Fra krig til atombombe",
                "compact": true,
                "events": [
                    {
                        "date": "1945",
                        "title": "Korea deles ved 38. breddegrad",
                        "description": "Etter Japans surrender deles Korea: Sovjet administrerer nord, USA sør."
                    },
                    {
                        "date": "1950",
                        "title": "Koreakrigen begynner",
                        "description": "Nord-Korea invaderer sør. USA og FN-styrker grep inn. Kina kommer til Nord-Koreas unnsetning."
                    },
                    {
                        "date": "1953",
                        "title": "Våpenhvile og DMZ",
                        "description": "Kampene stopper. DMZ etableres. Ingen fredsavtale – krigen er teknisk sett ikke avsluttet."
                    },
                    {
                        "date": "1985",
                        "title": "Første familiemøter",
                        "description": "For første gang siden krigen møtes noen skilte familier fra nord og sør – under streng overvåking."
                    },
                    {
                        "date": "2006",
                        "title": "Nord-Korea tester atombombe",
                        "description": "Nord-Korea gjennomfører sin første atomprøvesprengning. Konflikten eskalerer."
                    },
                    {
                        "date": "2018",
                        "title": "Kim og Moon møtes",
                        "description": "Nord-Koreas Kim Jong-un og Sør-Koreas Moon Jae-in møtes ved grensen. Trump møter Kim i Singapore. Spenningen avtar midlertidig."
                    }
                ]
            }
        },
        {
            "type": "header",
            "text": "Familier på hver sin side"
        },
        {
            "type": "text",
            "content": "Da krigen brøt ut, var Korea ett folk. Familier bodde over hele halvøya. Krigen delte dem over natten.\n\nVed våpenhvilen i 1953 ble millioner av koreanske familier splittet uten advarsel og uten å vite om de noen gang ville se hverandre igjen. De fleste gjorde det aldri. Det er ingen fri kommunikasjon mellom nord og sør – ingen telefon, ingen brev, ingen internett.\n\nSiden 1985 har noen få tusen mennesker fått delta i organiserte familiemøter: korte, overvåkede treff der søsken, foreldre og barn møtes etter 30, 40, 50 år. Rundt 57 000 sørkoreanske familier har søkt om å møte slektninger i nord. De fleste dør i ventetiden. Det anslås at over 100 000 sørkoreanske familier har mistet kontakten med slektninger i nord – for alltid."
        },
        {
            "type": "header",
            "text": "Naturreservat i krigens skygge"
        },
        {
            "type": "text",
            "content": "Her er paradokset som gjør DMZ unik blant verdens konfliktsoner: Fordi ingen mennesker har hatt lov til å gå inn i sonen på over 70 år, har naturen tatt den tilbake.\n\nDMZ er i dag hjem for over 5 000 plante- og dyrearter, inkludert mange truede fuglearter som hekker der fordi menneskene ikke forstyrrer dem. Den sibirske tranen – en kritisk truet fugl – overvintrer i DMZ. Asiatiske bjørner, leoparder og ulver er observert. Det er et utilsiktet naturreservat skapt av krigen – og av politisk fastlåsthet som har vart i generasjoner.\n\nDette er den stille, absurde sannheten om DMZ: Menneskene som bor rundt den, er splittet fra sine nærmeste. Men fuglene som flyr fritt over grensen bryr seg ikke om 38. breddegrad."
        },
        {
            "type": "header",
            "text": "Hva skjer i dag?"
        },
        {
            "type": "text",
            "content": "Nord-Korea er i dag ett av verdens mest lukkede og autoritære regimer. Landet har utviklet atomvåpen og langtrekkende missiler. USA og Sør-Korea holder regelmessige militærøvelser som Nord-Korea ser som en trussel. Nord-Korea svarer med rakettprøver.\n\nI 2018 skapte diplomatiske møter mellom Kim Jong-un og Sør-Koreas president, og mellom Kim og USAs president Donald Trump, håp om fremgang. De konkrete resultatene ble minimale. Spenningen er i dag like høy som noen gang.\n\nKorea er det sterkeste beviset på at delte samfunn ikke alltid løser seg. Som [Berlinmuren](/historie/den-kalde-krigen/berlinmuren) minner oss om, kan slike grenser falle overraskende raskt. Men Korea minner oss om at de kan stå enda lengre enn noen trodde mulig."
        },
        {
            "type": "component",
            "name": "Quiz",
            "props": {
                "questions": [
                    {
                        "question": "Hva betyr «DMZ»?",
                        "options": [
                            "Defence Military Zone",
                            "Demilitarized Zone",
                            "Democratic Military Zone",
                            "Division and Military Zone"
                        ],
                        "answer": "Demilitarized Zone"
                    },
                    {
                        "question": "Hvorfor er Korea teknisk sett fortsatt i krig?",
                        "options": [
                            "Nord-Korea avviste våpenhvilen i 1953",
                            "Det ble aldri signert en fredsavtale – bare en våpenhvile",
                            "USA og Nord-Korea byttet ikke fanger",
                            "Sør-Korea nekter å anerkjenne Nord-Korea som stat"
                        ],
                        "answer": "Det ble aldri signert en fredsavtale – bare en våpenhvile"
                    },
                    {
                        "question": "Hva er det paradoksale med DMZ som naturområde?",
                        "options": [
                            "Det er plantet trær der av FN",
                            "Sone er kunstig laget for å ligne natur",
                            "Fordi ingen mennesker slipper inn, har naturen tatt sonen tilbake og skapt et utilsiktet naturreservat",
                            "Nord-Korea bruker DMZ til å dyrke mat"
                        ],
                        "answer": "Fordi ingen mennesker slipper inn, har naturen tatt sonen tilbake og skapt et utilsiktet naturreservat"
                    },
                    {
                        "question": "Hva skjedde med koreanske familier da DMZ ble etablert?",
                        "options": [
                            "Alle fikk tillatelse til å velge hvilken side de ville bo på",
                            "Millioner av familier ble splittet og de fleste har aldri møttes igjen",
                            "FN organiserte rask gjenforening av alle familier",
                            "Familier ble jevnlig fraktet mellom nord og sør"
                        ],
                        "answer": "Millioner av familier ble splittet og de fleste har aldri møttes igjen"
                    }
                ]
            }
        }
    ],
    "quiz": [
        {
            "id": "q1",
            "question": "Hva betyr «DMZ»?",
            "options": [
                "Defence Military Zone",
                "Demilitarized Zone",
                "Democratic Military Zone",
                "Division and Military Zone"
            ],
            "correctAnswer": 1
        },
        {
            "id": "q2",
            "question": "Hvorfor er Korea teknisk sett fortsatt i krig?",
            "options": [
                "Nord-Korea avviste våpenhvilen i 1953",
                "Det ble aldri signert en fredsavtale – bare en våpenhvile",
                "USA og Nord-Korea byttet ikke fanger",
                "Sør-Korea nekter å anerkjenne Nord-Korea som stat"
            ],
            "correctAnswer": 1
        },
        {
            "id": "q3",
            "question": "Hva er det paradoksale med DMZ som naturområde?",
            "options": [
                "Det er plantet trær der av FN",
                "Sone er kunstig laget for å ligne natur",
                "Fordi ingen mennesker slipper inn, har naturen tatt sonen tilbake og skapt et utilsiktet naturreservat",
                "Nord-Korea bruker DMZ til å dyrke mat"
            ],
            "correctAnswer": 2
        },
        {
            "id": "q4",
            "question": "Hva skjedde med koreanske familier da DMZ ble etablert?",
            "options": [
                "Alle fikk tillatelse til å velge hvilken side de ville bo på",
                "Millioner av familier ble splittet og de fleste har aldri møttes igjen",
                "FN organiserte rask gjenforening av alle familier",
                "Familier ble jevnlig fraktet mellom nord og sør"
            ],
            "correctAnswer": 1
        }
    ],
    "createdDate": "2026-04-08T00:00:00Z",
    "lastUpdated": "2026-04-08T00:00:00Z"
}
